requirements.txt
pyassembly/__init__.py
pyassembly/main.py
pyassembly-2.3.dist-info/LICENSE.txt
pyassembly-2.3.dist-info/METADATA
pyassembly-2.3.dist-info/WHEEL
pyassembly-2.3.dist-info/entry_points.txt
pyassembly-2.3.dist-info/top_level.txt
pyassembly-2.3.dist-info/RECORD
