Metadata-Version: 2.1
Name: pyassembly
Version: 2.3
Summary: Creates an egg or a zip distribution with all its transitive dependencies
Home-page: https://github.com/alekseyig/pyassembly
Author: Aleksey Zhukov
Author-email: alekseyig@hotmail.com
License: MIT
Keywords: egg,zip,transitive,dependencies,assembly
Platform: any
Requires-Dist: pip (>=9.0.3)
Requires-Dist: setuptools
